portone_mcp_server/__init__.py
portone_mcp_server/server.py
portone_mcp_server/loader/__init__.py
portone_mcp_server/loader/markdown.py
portone_mcp_server/loader/schema.py
portone_mcp_server/resources/instructions.md
portone_mcp_server/resources/docs/README.md
portone_mcp_server/resources/docs/v1-docs-full.md
portone_mcp_server/resources/docs/v2-docs-full.md
portone_mcp_server/resources/docs/website-links.md
portone_mcp_server/resources/docs/api/backward-compatibility.md
portone_mcp_server/resources/docs/blog/posts/2024-02/v2-oom.md
portone_mcp_server/resources/docs/blog/posts/2024-02/v2-webhook.md
portone_mcp_server/resources/docs/blog/posts/2024-02/v2-zio.md
portone_mcp_server/resources/docs/blog/posts/2024-03/tgs.md
portone_mcp_server/resources/docs/blog/posts/2024-04/gcp-datastream.md
portone_mcp_server/resources/docs/blog/posts/2024-04/solid.md
portone_mcp_server/resources/docs/blog/posts/2024-07/v2-event-sourcing-basic.md
portone_mcp_server/resources/docs/help/api-sdk-2024-12-19.md
portone_mcp_server/resources/docs/help/applepay.md
portone_mcp_server/resources/docs/help/content100000.md
portone_mcp_server/resources/docs/help/content100002.md
portone_mcp_server/resources/docs/help/content100004.md
portone_mcp_server/resources/docs/help/content100014.md
portone_mcp_server/resources/docs/help/content100015.md
portone_mcp_server/resources/docs/help/content100016.md
portone_mcp_server/resources/docs/help/content100020.md
portone_mcp_server/resources/docs/help/content100022.md
portone_mcp_server/resources/docs/help/content100023.md
portone_mcp_server/resources/docs/help/content100024.md
portone_mcp_server/resources/docs/help/content100025.md
portone_mcp_server/resources/docs/help/content100026.md
portone_mcp_server/resources/docs/help/content100027.md
portone_mcp_server/resources/docs/help/content100029.md
portone_mcp_server/resources/docs/help/content100030.md
portone_mcp_server/resources/docs/help/content100033.md
portone_mcp_server/resources/docs/opi/ko/support/code-info/card-code.md
portone_mcp_server/resources/docs/opi/ko/support/code-info/code.md
portone_mcp_server/resources/docs/opi/ko/support/code-info/pg-1.md
portone_mcp_server/resources/docs/opi/ko/support/code-info/pg-2.md
portone_mcp_server/resources/docs/opi/ko/support/code-info/pg-3.md
portone_mcp_server/resources/docs/opi/ko/support/code-info/pg.md
portone_mcp_server/resources/docs/opi/ko/support/code-info/portone-code.md
portone_mcp_server/resources/docs/opi/ko/support/code-info/readme.md
portone_mcp_server-0.12.1.dist-info/METADATA
portone_mcp_server-0.12.1.dist-info/WHEEL
portone_mcp_server-0.12.1.dist-info/entry_points.txt
portone_mcp_server-0.12.1.dist-info/licenses/LICENSE
portone_mcp_server-0.12.1.dist-info/RECORD
